BoilerTest/__init__.py
BoilerTest/main.py
BoilerTest-1.0.4.dist-info/METADATA
BoilerTest-1.0.4.dist-info/WHEEL
BoilerTest-1.0.4.dist-info/entry_points.txt
BoilerTest-1.0.4.dist-info/top_level.txt
BoilerTest-1.0.4.dist-info/RECORD
